LICENSE
MANIFEST.in
README
setup.py
statin/__init__.py
statin/conf.py
statin/statin.py
statin.egg-info/PKG-INFO
statin.egg-info/SOURCES.txt
statin.egg-info/dependency_links.txt
statin.egg-info/entry_points.txt
statin.egg-info/top_level.txt